pipeoptz/__init__.py
pipeoptz/node.py
pipeoptz/optimizer.py
pipeoptz/parameter.py
pipeoptz/pipeline.py
pipeoptz-0.1.5.dist-info/licenses/LICENSE
pipeoptz-0.1.5.dist-info/METADATA
pipeoptz-0.1.5.dist-info/WHEEL
pipeoptz-0.1.5.dist-info/top_level.txt
pipeoptz-0.1.5.dist-info/RECORD
