Metadata-Version: 2.4
Name: pipeoptz
Version: 0.1.5
Summary: A Python library for creating and optimizing processing pipeline.
Author-email: Nicolas PENGOV <nicolas.pengov@etu.ec-lyon.fr>
License: MIT License
Project-URL: Homepage, https://github.com/centralelyon/pipeoptz
Project-URL: Issues, https://github.com/centralelyon/pipeoptz/issues
Classifier: Programming Language :: Python :: 3
Classifier: License :: OSI Approved :: MIT License
Classifier: Operating System :: OS Independent
Requires-Python: >=3.9
License-File: LICENSE
Requires-Dist: numpy
Requires-Dist: scikit-learn
Requires-Dist: scipy
Provides-Extra: examples
Requires-Dist: matplotlib; extra == "examples"
Requires-Dist: opencv-python; extra == "examples"
Requires-Dist: Pillow; extra == "examples"
Requires-Dist: ipywidgets; extra == "examples"
Requires-Dist: jupyter; extra == "examples"
Provides-Extra: dev
Requires-Dist: pytest; extra == "dev"
Requires-Dist: ruff; extra == "dev"
Requires-Dist: pytest-cov; extra == "dev"
Dynamic: license-file
